cengal_poly_build/__init__.py
cengal_poly_build/versions/__init__.py
cengal_poly_build/versions/v_0/__init__.py
cengalpolybuild-0.0.1.dist-info/METADATA
cengalpolybuild-0.0.1.dist-info/WHEEL
cengalpolybuild-0.0.1.dist-info/licenses/LICENSE.md
cengalpolybuild-0.0.1.dist-info/licenses/NOTICE
cengalpolybuild-0.0.1.dist-info/RECORD
